gbif_dl/__init__.py
gbif_dl/runners.py
gbif_dl/utils.py
gbif_dl/generators/__init__.py
gbif_dl/generators/api.py
gbif_dl/generators/dwca.py
gbif_dl/stores/__init__.py
gbif_dl/stores/dl_async.py
gbif_dl/stores/export.py
gbif_dl-0.1.1.dist-info/LICENSE
gbif_dl-0.1.1.dist-info/METADATA
gbif_dl-0.1.1.dist-info/WHEEL
gbif_dl-0.1.1.dist-info/top_level.txt
gbif_dl-0.1.1.dist-info/RECORD
