Metadata-Version: 2.1
Name: gbif-dl
Version: 0.1.1
Summary: Machine learning data loaders for GBIF
Home-page: https://github.com/plantnet/gbif-dl
Author: Fabian-Robert Stöter (Inria)
Author-email: fabian-robert.stoter@inria.fr
License: MIT
Classifier: Development Status :: 4 - Beta
Classifier: Programming Language :: Python :: 3
Classifier: Programming Language :: Python :: 3.6
Classifier: Programming Language :: Python :: 3.7
Classifier: Programming Language :: Python :: 3.8
Classifier: Programming Language :: Python :: 3.9
Classifier: License :: OSI Approved :: MIT License
Classifier: Operating System :: OS Independent
Requires-Python: >=3.6
License-File: LICENSE
Requires-Dist: aiofiles (>=0.6.0)
Requires-Dist: aiohttp (>=3.7.2)
Requires-Dist: aiohttp-retry (>=2.3)
Requires-Dist: aiostream (>=0.4.3)
Requires-Dist: pygbif (>=0.5.0)
Requires-Dist: requests-cache (==0.7.4)
Requires-Dist: pescador (>=2.1.0)
Requires-Dist: python-dwca-reader
Requires-Dist: filetype (>=1.0.0)
Requires-Dist: tqdm
Requires-Dist: typing-extensions ; python_version < "3.8"
Provides-Extra: docs
Requires-Dist: pdoc3 ; extra == 'docs'
Provides-Extra: tests
Requires-Dist: pytest ; extra == 'tests'
